{"Generalities, riding horseback, agg.":{"remedies":{"Ars.":1,"Bell.":2,"Bry.":1,"Graph.":2,"Lil-t.":2,"Mag-m.":1,"Meph.":1,"Nat-c.":2,"Sep.":3,"Sil.":1,"Spig.":1,"Sul-ac.":2,"Valer.":1},"chapter_id":"13"},"Generalities, riding horseback":{"remedies":{"Ars.":1,"Bell.":2,"Brom.":1,"Bry.":1,"Calc.":1,"Graph.":2,"Lil-t.":2,"Lyc.":1,"Mag-m.":1,"Meph.":1,"Nat-c.":2,"Sep.":3,"Sil.":1,"Spig.":1,"Sul-ac.":2,"Valer.":1},"chapter_id":"13"},"Generalities, riding horseback, amel.":{"remedies":{"Brom.":1,"Calc.":1,"Lyc.":1},"chapter_id":"13"}}