{"Mind, abstraction of mind":{"remedies":{"Alum.":1,"Aml-n.":1,"Camph.":1,"Cann-i.":2,"Carb-ac.":1,"Caust.":1,"Cic.":1,"Con.":1,"Cycl.":1,"Elaps":1,"Guai.":1,"Hell.":2,"Hyos.":2,"Kreos.":2,"Laur.":1,"Lyc.":1,"Lyss.":1,"Mez.":1,"Nat-m.":2,"Nux-m.":3,"Oena.":2,"Onos.":2,"Op.":1,"Ph-ac.":1,"Phos.":3,"Plat.":1,"Sabad.":1,"Sec.":1,"Sil.":1,"Stram.":1,"Sulph.":2,"Vesp.":1,"Visc.":2,"Agath-a.":2,"Dream.":1,"Falco-p.":3,"Herin.":1,"Lava-f.":1,"LSD.":1,"Salx-f.":1},"chapter_id":"20"},"Mind, abstraction of mind, morning":{"remedies":{"Guai.":1},"chapter_id":"20"},"Mind, abstraction of mind, driving the car, when":{"remedies":{"Falco-p.":2,"LSD.":1,"Salx-f.":1},"chapter_id":"20"}}