{"Mind, jesting":{"remedies":{"Acon.":2,"Aeth.":1,"Aloe":1,"Am-c.":1,"Ang.":1,"Apis":1,"Arg.":1,"Ars.":1,"Bar-c.":1,"Bell.":1,"Bor.":1,"Bov.":1,"Bry.":1,"Calc.":1,"Cann-i.":1,"Caps.":2,"Carb-an.":1,"Carb-v.":1,"Cic.":2,"Cina":2,"Cocc.":2,"Croc.":3,"Cupr.":1,"Cycl.":1,"Glon.":1,"Hyos.":1,"Ign.":3,"Ip.":1,"Kali-i.":2,"Lach.":2,"Lyc.":1,"Meny.":1,"Merl.":1,"Merc.":1,"Nat-m.":1,"Nux-m.":2,"Nux-v.":1,"Op.":1,"Plat.":1,"Puls.":1,"Rhus-r.":1,"Sabin.":1,"Sars.":1,"Sec.":1,"Sil.":1,"Spig.":1,"Spong.":1,"Stram.":2,"Sulph.":1,"Sul-ac.":1,"Tab.":1,"Tanac.":1,"Tarent.":2,"Thuj.":1,"Verat.":2,"Agath-a.":2,"Falco-p.":1,"Herin.":1,"LSD.":1},"chapter_id":"20"},"Mind, jesting, averse to":{"remedies":{"Acon.":2,"Am-c.":1,"Ang.":1,"Apis":1,"Ars.":1,"Bor.":1,"Bov.":1,"Caps.":1,"Carb-an.":1,"Cina":2,"Cocc.":1,"Cycl.":1,"Merc.":1,"Nat-m.":1,"Nux-v.":1,"Puls.":1,"Sabin.":1,"Sil.":1,"Spig.":1,"Sulph.":1,"Thuj.":1,"Falco-p.":1,"LSD.":1},"chapter_id":"20"},"Mind, jesting, malicious":{"remedies":{"Ars.":1},"chapter_id":"20"},"Mind, jesting, ridiculous or foolish":{"remedies":{"Bell.":1,"Cic.":2,"Croc.":1,"Hyos.":1,"Stram.":2,"Tanac.":1,"Verat.":2,"Falco-p.":1},"chapter_id":"20"},"Mind, jesting, puns, makes":{"remedies":{"Cann-i.":1},"chapter_id":"20"},"Mind, jesting, indifference, after":{"remedies":{"Meny.":1},"chapter_id":"20"},"Mind, jesting, gravity, after":{"remedies":{"Plat.":1},"chapter_id":"20"}}