{"Abdomen, motion, agg.":{"remedies":{"Aloe":1,"Alum.":1,"Ang.":1,"Ant-c.":1,"Arg-n.":1,"Arn.":1,"Asar.":1,"Aur.":1,"Bar-c.":1,"Bell.":1,"Bry.":3,"Calc.":1,"Cann-s.":1,"Caps.":2,"Chin.":3,"Cocc.":3,"Colch.":2,"Cycl.":2,"Dig.":1,"Graph.":1,"Ip.":2,"Kali-n.":1,"Kreos.":1,"Lyc.":1,"Mag-m.":2,"Merc-c.":3,"Merc.":3,"Mez.":1,"Mur-ac.":1,"Nat-c.":1,"Nat-m.":1,"Nux-v.":3,"Plb.":1,"Puls.":3,"Ran-b.":2,"Rheum":1,"Rhus-t.":1,"Sec.":1,"Sep.":2,"Staph.":3,"Stram.":1,"Zinc.":1},"chapter_id":"0"},"Abdomen, motion":{"remedies":{"Aloe":1,"Alum.":1,"Am-c.":1,"Ang.":1,"Ant-c.":1,"Ant-t.":1,"Arg-n.":1,"Arn.":1,"Asar.":1,"Aur.":1,"Bar-c.":1,"Bell.":1,"Bov.":1,"Bry.":3,"Calc.":1,"Cann-s.":1,"Canth.":1,"Caps.":2,"Cham.":1,"Chin.":3,"Cocc.":3,"Colch.":2,"Coloc.":2,"Con.":1,"Cycl.":2,"Dig.":1,"Dulc.":1,"Graph.":1,"Ip.":2,"Kali-n.":1,"Kreos.":1,"Lyc.":1,"Mag-m.":2,"Meny.":2,"Merc-c.":3,"Merc.":3,"Mez.":1,"Mur-ac.":1,"Nat-c.":1,"Nat-m.":1,"Nux-v.":3,"Op.":1,"Petr.":2,"Phos.":1,"Plb.":1,"Puls.":3,"Ran-b.":2,"Rheum":1,"Rhus-t.":2,"Sec.":1,"Sep.":2,"Staph.":3,"Stram.":1,"Sulph.":2,"Zinc.":1},"chapter_id":"0"},"Abdomen, motion, amel.":{"remedies":{"Am-c.":1,"Ant-t.":1,"Aur.":1,"Bov.":1,"Calc.":1,"Canth.":1,"Cham.":1,"Coloc.":2,"Con.":1,"Dulc.":1,"Kali-n.":1,"Meny.":2,"Op.":1,"Petr.":2,"Phos.":1,"Puls.":2,"Rhus-t.":2,"Sep.":1,"Sulph.":2},"chapter_id":"0"},"Abdomen, motion, after, agg.":{"remedies":{"Arn.":1,"Puls.":3},"chapter_id":"0"}}