{"Urethra, stricture":{"remedies":{"Acon.":1,"Agar.":1,"Ant-t.":1,"Apis":2,"Arg-n.":2,"Bell.":2,"Berb.":2,"Bry.":1,"Calc.":2,"Camph.":1,"Cann-s.":2,"Canth.":3,"Carb-v.":1,"Chim.":2,"Chin.":1,"Cic.":2,"Cinnb.":1,"Clem.":3,"Coc-c.":1,"Con.":2,"Cop.":1,"Dig.":2,"Dios.":2,"Dulc.":2,"Eucal.":1,"Gels.":2,"Graph.":2,"Indg.":2,"Iod.":2,"Kali-i.":2,"Merc.":2,"Nat-m.":2,"Nit-ac.":3,"Nux-v.":2,"Op.":2,"Petr.":3,"Petros.":2,"Ph-ac.":2,"Plb.":2,"Prun.":2,"Puls.":3,"Sec.":2,"Sep.":1,"Sil.":2,"Stram.":1,"Sulph.":2,"Tarent.":1,"Thuj.":1},"chapter_id":"33"},"Urethra, stricture, spasmodic":{"remedies":{"Apis":1,"Bell.":2,"Berb.":1,"Camph.":1,"Canth.":3,"Carb-v.":1,"Cic.":2,"Clem.":2,"Con.":1,"Cop.":1,"Dios.":2,"Eucal.":1,"Gels.":2,"Indg.":1,"Nit-ac.":3,"Nux-v.":2,"Op.":2,"Ph-ac.":2,"Plb.":2,"Prun.":2,"Sec.":2,"Stram.":1},"chapter_id":"33"},"Urethra, stricture, sensation, of":{"remedies":{"Bry.":1,"Coc-c.":1,"Dig.":1,"Graph.":1,"Thuj.":1},"chapter_id":"33"},"Urethra, stricture, spasmodic, morning":{"remedies":{"Carb-v.":1},"chapter_id":"33"}}