{"Abdomen, breakfast":{"remedies":{"Agar.":1,"All-c.":1,"Alum.":1,"Am-c.":1,"Apoc.":1,"Arum-m.":1,"Bor.":1,"Cahin.":1,"Calc.":1,"Calc-s.":1,"Carb-v.":2,"Caust.":1,"Chin-ar.":1,"Cic.":1,"Cycl.":1,"Eupi.":1,"Gels.":1,"Graph.":1,"Grat.":1,"Ham.":1,"Hydr.":1,"Ign.":2,"Kali-bi.":1,"Kali-c.":1,"Kali-n.":1,"Kali-p.":1,"Laur.":1,"Lyc.":1,"Mag-m.":1,"Nat-m.":1,"Nat-p.":1,"Nat-s.":3,"Nux-m.":1,"Nux-v.":1,"Phos.":1,"Plan.":1,"Plb.":1,"Raph.":1,"Rhod.":1,"Sars.":1,"Spong.":1,"Stront-c.":1,"Sulph.":2,"Thuj.":1,"Zinc.":3,"Carbn-s.":1},"chapter_id":"0"},"Abdomen, breakfast, agg., after":{"remedies":{"Agar.":1,"Cic.":1,"Cycl.":1,"Graph.":1,"Kali-c.":1,"Kali-n.":1,"Laur.":1,"Lyc.":1,"Mag-m.":1,"Nat-m.":1,"Nux-m.":1,"Nux-v.":1,"Phos.":1,"Plb.":1,"Rhod.":1,"Sars.":1,"Stront-c.":1,"Thuj.":1,"Zinc.":3},"chapter_id":"0"},"Abdomen, breakfast, agg.":{"remedies":{"Agar.":1,"Alum.":1,"Cic.":1,"Cycl.":1,"Graph.":1,"Kali-c.":1,"Kali-n.":1,"Laur.":1,"Lyc.":1,"Mag-m.":1,"Nat-m.":1,"Nux-m.":1,"Nux-v.":1,"Phos.":1,"Plb.":1,"Rhod.":1,"Sars.":1,"Stront-c.":1,"Thuj.":1,"Zinc.":3},"chapter_id":"0"},"Abdomen, breakfast, agg., during":{"remedies":{"Alum.":1},"chapter_id":"0"},"Abdomen, breakfast, amel., after":{"remedies":{"Mag-m.":1},"chapter_id":"0"}}