{"Vertigo, menses, before":{"remedies":{"Acon.":1,"Agn.":1,"Bor.":1,"Bov.":1,"Bry.":1,"Calc.":1,"Calc-p.":2,"Caul.":2,"Chel.":1,"Con.":2,"Lach.":2,"Nux-m.":1,"Phos.":1,"Puls.":2,"Verat.":2,"Zinc.":2},"chapter_id":"35"},"Vertigo, menses, during agg.":{"remedies":{"Acon.":2,"Am-c.":1,"Ant-t.":1,"Arg-n.":1,"Bor.":1,"Bov.":1,"Brom.":1,"Cact.":1,"Calc.":2,"Calc-p.":1,"Carb-v.":1,"Caul.":1,"Caust.":2,"Con.":2,"Croc.":2,"Cub.":1,"Cycl.":2,"Elaps":1,"Ferr.":1,"Ferr-p.":2,"Gels.":2,"Graph.":1,"Iod.":2,"Kali-bi.":2,"Lach.":2,"Lyc.":1,"Mosch.":1,"Nux-v.":1,"Ph-ac.":2,"Phos.":1,"Plat.":1,"Puls.":3,"Sec.":2,"Sulph.":2,"Thuj.":1,"Tril.":1,"Uran-n.":1,"Ust.":1,"Carbn-s.":1},"chapter_id":"35"},"Vertigo, menses, suppressed":{"remedies":{"Acon.":2,"Bry.":1,"Calc.":1,"Cimic.":1,"Con.":1,"Cycl.":3,"Gels.":1,"Lach.":1,"Nux-v.":1,"Phos.":1,"Plat.":1,"Puls.":3,"Sabin.":1,"Sep.":1,"Sil.":1,"Sulph.":1,"Verat.":1,"Zinc.":1},"chapter_id":"35"},"Vertigo, menses":{"remedies":{"Acon.":2,"Agar.":1,"Agn.":1,"All-s.":1,"Am-c.":1,"Ant-t.":1,"Arg-n.":1,"Bor.":1,"Bov.":1,"Brom.":1,"Bry.":1,"Cact.":1,"Calc.":2,"Calc-p.":2,"Carb-v.":1,"Caul.":2,"Caust.":2,"Chel.":1,"Cimic.":1,"Con.":2,"Croc.":2,"Cub.":1,"Cycl.":3,"Elaps":1,"Ferr.":1,"Ferr-p.":2,"Gels.":2,"Graph.":1,"Iod.":2,"Kali-bi.":2,"Lach.":2,"Lyc.":1,"Mosch.":1,"Nat-m.":1,"Nux-m.":1,"Nux-v.":1,"Ph-ac.":2,"Phos.":1,"Plat.":1,"Puls.":3,"Sabin.":1,"Sec.":2,"Sep.":1,"Sil.":1,"Sulph.":2,"Thuj.":1,"Tril.":1,"Uran-n.":1,"Ust.":1,"Verat.":2,"Zinc.":2,"Carbn-s.":1},"chapter_id":"35"},"Vertigo, menses, during":{"remedies":{"Acon.":2,"All-s.":1,"Am-c.":1,"Ant-t.":1,"Arg-n.":1,"Bor.":1,"Bov.":1,"Brom.":1,"Cact.":1,"Calc.":2,"Calc-p.":1,"Carb-v.":1,"Caul.":1,"Caust.":2,"Con.":2,"Croc.":2,"Cub.":1,"Cycl.":2,"Elaps":1,"Ferr.":1,"Ferr-p.":2,"Gels.":2,"Graph.":1,"Iod.":2,"Kali-bi.":2,"Lach.":2,"Lyc.":1,"Mosch.":1,"Nux-v.":1,"Ph-ac.":2,"Phos.":1,"Plat.":1,"Puls.":3,"Sec.":2,"Sulph.":2,"Thuj.":1,"Tril.":1,"Uran-n.":1,"Ust.":1,"Carbn-s.":1},"chapter_id":"35"},"Vertigo, menses, after":{"remedies":{"Agar.":1,"Ant-t.":1,"Con.":1,"Nat-m.":1,"Puls.":1,"Ust.":1},"chapter_id":"35"},"Vertigo, menses, during, amel.":{"remedies":{"All-s.":1,"Lach.":1},"chapter_id":"35"},"Vertigo, menses, during, stooping, on":{"remedies":{"Calc.":2,"Caust.":1},"chapter_id":"35"},"Vertigo, menses, during, stooping, on, and rising again":{"remedies":{"Calc.":2},"chapter_id":"35"},"Vertigo, menses, during, stooping":{"remedies":{"Calc.":2,"Caust.":1},"chapter_id":"35"},"Vertigo, menses, during, walking, while":{"remedies":{"Phos.":1},"chapter_id":"35"}}