{"Stool, gray":{"remedies":{"Aloe":1,"Ars.":3,"Asar.":1,"Aur.":2,"Bapt.":1,"Calc.":2,"Carb-v.":2,"Cench.":1,"Chel.":2,"Chim.":1,"Cist.":1,"Croto-t.":1,"Cupr.":1,"Dig.":2,"Hydr.":2,"Kali-c.":2,"Kreos.":1,"Lach.":2,"Lycps.":1,"Mag-m.":1,"Merc.":3,"Myric.":1,"Nat-m.":2,"Nat-s.":1,"Op.":3,"Ph-ac.":3,"Phos.":3,"Pic-ac.":1,"Plb.":1,"Psor.":1,"Rheum":1,"Sec.":1,"Sep.":1,"Sulph.":1,"Posit.":1},"chapter_id":"30"},"Stool, gray, whitish, in part":{"remedies":{"Nat-m.":1,"Phos.":3,"Plb.":1},"chapter_id":"30"}}