{"Mouth, membrane, palate covered with a false":{"remedies":{"Apis":1,"Iod.":2,"Ip.":1,"Lac-c.":2,"Lach.":2,"Lyc.":2,"Merc-cy.":1,"Merc-i-f.":1,"Merc.":2,"Mur-ac.":2,"Nat-p.":3,"Nit-ac.":2,"Sang.":2,"Seneg.":1,"Sulph.":1,"Zinc-m.":1},"chapter_id":"21"},"Mouth, membrane, palate covered with a false, velum":{"remedies":{"Apis":1,"Iod.":2,"Lach.":2,"Lyc.":2,"Merc-cy.":1,"Merc-i-f.":1,"Mur-ac.":2,"Sang.":2,"Seneg.":1},"chapter_id":"21"},"Mouth, membrane":{"remedies":{"Apis":1,"Arum-t.":3,"Bry.":1,"Hippoz.":1,"Iod.":2,"Ip.":1,"Kali-chl.":2,"Lac-c.":2,"Lach.":2,"Lyc.":2,"Merc-cy.":2,"Merc-i-f.":1,"Merc.":2,"Mur-ac.":2,"Nat-p.":3,"Nit-ac.":3,"Sang.":2,"Seneg.":1,"Sulph.":1,"Sul-ac.":2,"Zinc-m.":1},"chapter_id":"21"},"Mouth, membrane, false":{"remedies":{"Arum-t.":3,"Bry.":1,"Hippoz.":1,"Iod.":2,"Kali-chl.":2,"Lac-c.":2,"Merc-cy.":2,"Mur-ac.":2,"Nit-ac.":3,"Sul-ac.":2},"chapter_id":"21"},"Mouth, membrane, false, silvery white all over mouth":{"remedies":{"Kali-chl.":2,"Lac-c.":2,"Sul-ac.":1},"chapter_id":"21"},"Mouth, membrane, palate covered with a false, creamy":{"remedies":{"Nat-p.":1},"chapter_id":"21"},"Mouth, membrane, palate covered with a false, evening":{"remedies":{"Nat-p.":3},"chapter_id":"21"},"Mouth, membrane, false, tongue, on, tough and yellow":{"remedies":{"Nit-ac.":2},"chapter_id":"21"},"Mouth, membrane, false, whitish yellow":{"remedies":{"Nit-ac.":3,"Sul-ac.":2},"chapter_id":"21"},"Mouth, membrane, palate covered with a false, yellowish gray":{"remedies":{"Nit-ac.":1},"chapter_id":"21"},"Mouth, membrane, false, white coating like":{"remedies":{"Sul-ac.":1},"chapter_id":"21"},"Mouth, membrane, palate covered with a false, white":{"remedies":{"Zinc-m.":1},"chapter_id":"21"}}