{"Vision, myopia":{"remedies":{"Agar.":2,"Am-c.":3,"Anac.":2,"Ang.":2,"Ant-t.":3,"Apis":1,"Arg-n.":2,"Ars.":1,"Calc.":3,"Carb-v.":2,"Chin.":3,"Cimic.":1,"Coff-t.":1,"Con.":3,"Cycl.":3,"Dig.":1,"Euph.":1,"Euphr.":3,"Form.":2,"Gels.":2,"Graph.":2,"Grat.":1,"Hep.":2,"Hyos.":3,"Jab.":2,"Lach.":3,"Lyc.":3,"Meph.":2,"Mez.":1,"Nat-ar.":1,"Nat-c.":2,"Nat-m.":2,"Nat-p.":1,"Nit-ac.":3,"Petr.":3,"Ph-ac.":3,"Phos.":3,"Phys.":3,"Pic-ac.":2,"Plb.":2,"Psor.":1,"Puls.":3,"Raph.":1,"Ruta":3,"Sel.":1,"Spong.":1,"Stram.":3,"Sulph.":3,"Sul-ac.":3,"Syph.":1,"Thuj.":2,"Tub.":2,"Valer.":3,"Verb.":1,"Viol-o.":2,"Viol-t.":1,"Posit.":1,"Mang.":2,"Carbn-s.":1},"chapter_id":"36"},"Vision, myopia, reading, while":{"remedies":{"Agar.":1,"Grat.":1,"Lyc.":1},"chapter_id":"36"},"Vision, myopia, candlelight, sight agg. by, than by daylight":{"remedies":{"Arg-n.":1},"chapter_id":"36"},"Vision, myopia, exerting the eyes, after":{"remedies":{"Carb-v.":2},"chapter_id":"36"},"Vision, myopia, looking away from work amel.":{"remedies":{"Ph-ac.":1},"chapter_id":"36"}}