{"Head, jerking of":{"remedies":{"Agar.":2,"Alum.":1,"Arn.":2,"Ars.":1,"Atro.":1,"Bell.":3,"Bov.":1,"Caust.":1,"Chel.":1,"Cic.":2,"Cina":1,"Hyos.":2,"Hyper.":2,"Ign.":1,"Kali-c.":1,"Merc.":1,"Mygal.":1,"Nat-m.":2,"Nat-s.":2,"Nux-m.":2,"Nux-v.":1,"Ph-ac.":1,"Plb.":1,"Samb.":1,"Sep.":2,"Spong.":1,"Stram.":3,"Stront-c.":1,"Stry.":1,"Sumb.":1,"Ther.":1,"Verat-v.":1},"chapter_id":"16"},"Head, jerking of, backwards":{"remedies":{"Alum.":1,"Ars.":1,"Atro.":1,"Bov.":1,"Cic.":2,"Cina":1,"Hyper.":1,"Merc.":1,"Nux-m.":1,"Nux-v.":1,"Sep.":1,"Stry.":1},"chapter_id":"16"},"Head, jerking of, sleep, during":{"remedies":{"Arn.":2,"Hyper.":2},"chapter_id":"16"},"Head, jerking of, sleep":{"remedies":{"Arn.":2,"Hyper.":2},"chapter_id":"16"},"Head, jerking of, backwards and forwards":{"remedies":{"Ars.":1,"Nux-m.":1,"Sep.":1,"Stry.":1},"chapter_id":"16"},"Head, jerking of, walking quickly or ascending stairs, on":{"remedies":{"Bell.":3},"chapter_id":"16"},"Head, jerking of, here and there":{"remedies":{"Chel.":1,"Stram.":1,"Stront-c.":1},"chapter_id":"16"},"Head, jerking of, lying on the back, while":{"remedies":{"Cic.":2,"Hyper.":2},"chapter_id":"16"},"Head, jerking of, talking, while":{"remedies":{"Cic.":2},"chapter_id":"16"},"Head, jerking of, sleep, during, head jerks backwards":{"remedies":{"Hyper.":2},"chapter_id":"16"},"Head, jerking of, behind forward, from":{"remedies":{"Kali-c.":1,"Nux-m.":2,"Ph-ac.":1,"Spong.":1,"Stram.":2,"Stry.":1},"chapter_id":"16"},"Head, jerking of, one side to another, from":{"remedies":{"Kali-c.":1,"Nat-s.":1,"Nux-m.":1,"Plb.":1,"Samb.":1},"chapter_id":"16"},"Head, jerking of, right, to":{"remedies":{"Nat-s.":2},"chapter_id":"16"},"Head, jerking of, daytime":{"remedies":{"Sep.":2},"chapter_id":"16"},"Head, jerking of, involuntary, back and forward, while sitting":{"remedies":{"Sep.":1},"chapter_id":"16"},"Head, jerking of, sitting, while":{"remedies":{"Sep.":1},"chapter_id":"16"},"Head, jerking of, lying, the head jerks clear of the pillow":{"remedies":{"Stram.":3},"chapter_id":"16"},"Head, jerking of, head forward and knees upward during cough":{"remedies":{"Ther.":1},"chapter_id":"16"}}