{"Genitalia male, seminal emissions (nightly)":{"remedies":{"Absin.":1,"Acet-ac.":1,"Aesc.":1,"Agar.":2,"Agn.":2,"Aloe":1,"Alum.":2,"Am-c.":2,"Anac.":2,"Anan.":1,"Ant-c.":1,"Arg.":2,"Arg-n.":2,"Arn.":2,"Ars.":1,"Ars-i.":1,"Art-v.":1,"Aur.":2,"Bar-c.":3,"Bar-m.":2,"Bell.":2,"Berb.":2,"Bism-ox.":2,"Bor.":3,"Bov.":2,"Brom.":1,"Bry.":1,"Bufo":2,"Cahin.":1,"Calad.":1,"Calc-ar.":1,"Calc.":3,"Calc-p.":2,"Camph.":2,"Canth.":1,"Caps.":1,"Carb-an.":2,"Carb-v.":2,"Carb-ac.":1,"Carl.":2,"Cast.":2,"Caust.":2,"Cham.":2,"Chin.":3,"Chin-ar.":1,"Chin-s.":1,"Cic.":2,"Cimx.":2,"Cimic.":1,"Clem.":1,"Cob.":3,"Cocc.":2,"Coc-c.":2,"Coff.":1,"Coloc.":1,"Con.":3,"Cop.":1,"Cor-r.":2,"Croto-t.":1,"Cycl.":2,"Cypr.":3,"Daph.":1,"Dig.":3,"Dios.":3,"Elaps":1,"Ery-a.":2,"Ferr-ar.":1,"Ferr-i.":1,"Ferr.":2,"Ferr-p.":1,"Fl-ac.":1,"Form.":2,"Gels.":2,"Graph.":3,"Grat.":1,"Guai.":1,"Ham.":2,"Hep.":2,"Hyper.":1,"Ind.":1,"Iod.":2,"Iris":2,"Kali-ar.":1,"Kali-br.":2,"Kali-c.":2,"Kali-i.":1,"Kali-p.":3,"Lach.":2,"Lac-ac.":1,"Lact.":2,"Lyc.":3,"Mag-c.":1,"Mag-m.":2,"Med.":1,"Merc-c.":2,"Merc-i-f.":1,"Merc.":2,"Mosch.":2,"Naja":1,"Nat-ar.":2,"Nat-c.":3,"Nat-m.":3,"Nat-p.":3,"Nit-ac.":2,"Nuph.":2,"Nux-m.":2,"Nux-v.":3,"Ol-an.":1,"Onos.":2,"Op.":1,"Orig.":2,"Ox-ac.":1,"Par.":1,"Petr.":2,"Petros.":1,"Ph-ac.":3,"Phos.":3,"Pic-ac.":2,"Pip-m.":1,"Plan.":1,"Plat.":2,"Plb.":2,"Psor.":2,"Puls.":2,"Ran-b.":1,"Ran-s.":1,"Rhod.":2,"Rhus-t.":1,"Ruta":1,"Sabad.":2,"Sac-alb.":1,"Sang.":1,"Sars.":2,"Sel.":3,"Sep.":3,"Sil.":2,"Sin-a.":1,"Spig.":1,"Stann.":2,"Staph.":3,"Stram.":2,"Sulph.":3,"Tab.":1,"Tarax.":1,"Tarent.":2,"Ther.":1,"Thuj.":2,"Tub.":1,"Uran-n.":1,"Ust.":2,"Verb.":1,"Vib.":1,"Viol-o.":1,"Viol-t.":2,"Zinc.":2,"Zing.":1,"Carbn-s.":1},"chapter_id":"15"},"Genitalia male, seminal emissions (nightly), erections, without":{"remedies":{"Absin.":1,"Arg.":1,"Bell.":1,"Bism-ox.":1,"Calad.":1,"Carb-an.":1,"Chin.":2,"Cob.":3,"Con.":1,"Dios.":3,"Ery-a.":2,"Fl-ac.":1,"Gels.":2,"Graph.":3,"Ham.":1,"Kali-p.":1,"Mosch.":1,"Nat-c.":2,"Nat-m.":1,"Nat-p.":1,"Nuph.":2,"Nux-v.":1,"Op.":1,"Ph-ac.":2,"Phos.":1,"Sabad.":1,"Sars.":2,"Sel.":2,"Spig.":1,"Sulph.":1},"chapter_id":"15"},"Genitalia male, seminal emissions (nightly), stool, during":{"remedies":{"Acet-ac.":1,"Anac.":1,"Ars.":1,"Carb-v.":1,"Caust.":1,"Cimic.":1,"Con.":1,"Gels.":2,"Nat-m.":1,"Nuph.":2,"Petr.":2,"Ph-ac.":2,"Plb.":1,"Sel.":3,"Sep.":1,"Sil.":1,"Sulph.":1,"Viol-t.":1},"chapter_id":"15"},"Genitalia male, seminal emissions (nightly), stool":{"remedies":{"Acet-ac.":1,"Agn.":1,"Alum.":1,"Am-c.":1,"Anac.":1,"Ars.":1,"Carb-v.":1,"Caust.":1,"Cimic.":1,"Con.":1,"Gels.":2,"Hep.":1,"Nat-c.":1,"Nat-m.":1,"Nit-ac.":1,"Nuph.":2,"Petr.":2,"Ph-ac.":2,"Plb.":1,"Sel.":3,"Sep.":1,"Sil.":1,"Staph.":1,"Sulph.":1,"Viol-t.":1},"chapter_id":"15"},"Genitalia male, seminal emissions (nightly), dreams, without":{"remedies":{"Agar.":1,"Anac.":2,"Anan.":1,"Ant-c.":1,"Arg.":1,"Arg-n.":1,"Ars.":1,"Bell.":1,"Bism-ox.":1,"Camph.":2,"Carb-v.":1,"Cic.":1,"Con.":2,"Cor-r.":2,"Dig.":1,"Dios.":3,"Gels.":1,"Graph.":2,"Guai.":1,"Ham.":2,"Ind.":1,"Merc-i-f.":1,"Nat-c.":1,"Nat-p.":1,"Phos.":1,"Pic-ac.":2,"Pip-m.":1,"Sep.":1,"Sin-a.":1,"Stann.":2,"Verb.":1,"Vib.":1,"Zinc.":2},"chapter_id":"15"},"Genitalia male, seminal emissions (nightly), ameliorated, from":{"remedies":{"Agn.":1,"Calc.":1,"Calc-p.":2,"Elaps":1,"Lach.":2,"Naja":1,"Phos.":1,"Sil.":1,"Zinc.":1},"chapter_id":"15"},"Genitalia male, seminal emissions (nightly), coition, after":{"remedies":{"Agn.":2,"Am-c.":1,"Bar-c.":1,"Bry.":1,"Calc.":2,"Dig.":2,"Gels.":1,"Graph.":2,"Kali-c.":1,"Nat-m.":3,"Nat-p.":2,"Ph-ac.":2,"Phos.":2,"Rhod.":2,"Sep.":1},"chapter_id":"15"},"Genitalia male, seminal emissions (nightly), stool, difficult, during":{"remedies":{"Agn.":1,"Alum.":1,"Am-c.":1,"Anac.":1,"Con.":1,"Hep.":1,"Nat-c.":1,"Nit-ac.":1,"Petr.":2,"Sep.":1,"Staph.":1},"chapter_id":"15"},"Genitalia male, seminal emissions (nightly), morning":{"remedies":{"Aloe":1,"Cahin.":1,"Canth.":1,"Carb-v.":1,"Cham.":1,"Chin-s.":1,"Nat-m.":1,"Ph-ac.":2,"Pip-m.":1,"Psor.":1,"Thuj.":1},"chapter_id":"15"},"Genitalia male, seminal emissions (nightly), frequent":{"remedies":{"Alum.":2,"Am-c.":2,"Ant-c.":1,"Arg.":1,"Bar-c.":1,"Bar-m.":1,"Bor.":2,"Calc.":2,"Carb-an.":1,"Carb-v.":1,"Caust.":1,"Cob.":1,"Con.":2,"Dig.":1,"Ferr.":1,"Kali-c.":2,"Kali-p.":1,"Lach.":1,"Lyc.":1,"Mag-m.":1,"Nat-c.":2,"Nat-m.":1,"Nat-p.":2,"Nit-ac.":1,"Nux-v.":3,"Op.":1,"Petr.":1,"Ph-ac.":3,"Phos.":1,"Plb.":2,"Puls.":2,"Sac-alb.":1,"Sars.":1,"Sep.":2,"Stann.":1,"Staph.":3,"Sulph.":1},"chapter_id":"15"},"Genitalia male, seminal emissions (nightly), masturbation, after":{"remedies":{"Alum.":2,"Arg.":1,"Chin.":3,"Dig.":2,"Graph.":2,"Nux-v.":3,"Ph-ac.":2,"Phos.":1,"Puls.":2,"Sars.":2,"Sep.":3,"Staph.":3,"Tarent.":2,"Ust.":1},"chapter_id":"15"},"Genitalia male, seminal emissions (nightly), frequent, leaning the back against anything":{"remedies":{"Ant-c.":1},"chapter_id":"15"},"Genitalia male, seminal emissions (nightly), caresses, during":{"remedies":{"Arn.":2,"Con.":3,"Gels.":2,"Nat-c.":2,"Nux-v.":2,"Petr.":1,"Phos.":2,"Sars.":2,"Sel.":2,"Ust.":1},"chapter_id":"15"},"Genitalia male, seminal emissions (nightly), diarrhea, during":{"remedies":{"Ars.":1},"chapter_id":"15"},"Genitalia male, seminal emissions (nightly), waking, on":{"remedies":{"Ars.":1,"Naja":1,"Pic-ac.":1},"chapter_id":"15"},"Genitalia male, seminal emissions (nightly), spasms, with":{"remedies":{"Art-v.":1,"Grat.":1,"Nat-p.":2},"chapter_id":"15"},"Genitalia male, seminal emissions (nightly), frequent, in an old man":{"remedies":{"Bar-c.":1,"Caust.":1,"Nat-c.":1},"chapter_id":"15"},"Genitalia male, seminal emissions (nightly), daytime":{"remedies":{"Canth.":1,"Ery-a.":1,"Gels.":1,"Graph.":1,"Nux-v.":3,"Ust.":1},"chapter_id":"15"},"Genitalia male, seminal emissions (nightly), morning, in bed, penis relaxed":{"remedies":{"Canth.":1},"chapter_id":"15"},"Genitalia male, seminal emissions (nightly), afternoon, sleep, during":{"remedies":{"Caust.":1,"Clem.":1,"Merc.":1,"Phos.":1,"Sulph.":1},"chapter_id":"15"},"Genitalia male, seminal emissions (nightly), unconscious":{"remedies":{"Caust.":1,"Dios.":2,"Ham.":2,"Ind.":1,"Lach.":1,"Merc-i-f.":1,"Nat-p.":2,"Plan.":1,"Plb.":1,"Sel.":2,"Sep.":2,"Uran-n.":1},"chapter_id":"15"},"Genitalia male, seminal emissions (nightly), back, while lying on":{"remedies":{"Cob.":1,"Coloc.":1,"Hyper.":1},"chapter_id":"15"},"Genitalia male, seminal emissions (nightly), woman, while frolicking with a":{"remedies":{"Con.":3,"Phos.":2,"Sars.":1},"chapter_id":"15"},"Genitalia male, seminal emissions (nightly), woman":{"remedies":{"Con.":3,"Nux-v.":2,"Phos.":2,"Sars.":1,"Ust.":1},"chapter_id":"15"},"Genitalia male, seminal emissions (nightly), urinating, after":{"remedies":{"Daph.":1,"Kali-c.":1},"chapter_id":"15"},"Genitalia male, seminal emissions (nightly), excitement of fancy, without":{"remedies":{"Dios.":1,"Phos.":1},"chapter_id":"15"},"Genitalia male, seminal emissions (nightly), morning, stool, during":{"remedies":{"Nat-m.":1},"chapter_id":"15"},"Genitalia male, seminal emissions (nightly), night, every":{"remedies":{"Nat-m.":2,"Nat-p.":3,"Pic-ac.":2,"Tarax.":1},"chapter_id":"15"},"Genitalia male, seminal emissions (nightly), woman, when in the presence of a":{"remedies":{"Nux-v.":2,"Ust.":1},"chapter_id":"15"},"Genitalia male, seminal emissions (nightly), morning, during pressing at":{"remedies":{"Ph-ac.":2},"chapter_id":"15"},"Genitalia male, seminal emissions (nightly), colic, during":{"remedies":{"Plb.":1},"chapter_id":"15"},"Genitalia male, seminal emissions (nightly), forenoon, sitting, while":{"remedies":{"Sulph.":1},"chapter_id":"15"}}