{"Genitalia female, dryness":{"remedies":{"Acon.":2,"Ars.":2,"Bell.":2,"Berb.":2,"Ferr.":2,"Graph.":2,"Lyc.":2,"Lycps.":1,"Nat-m.":3,"Puls.":1,"Sep.":3,"Spira.":1,"Salx-f.":1},"chapter_id":"14"},"Genitalia female, dryness, vagina":{"remedies":{"Acon.":2,"Ars.":2,"Bell.":2,"Berb.":2,"Ferr.":2,"Graph.":2,"Lyc.":2,"Lycps.":1,"Nat-m.":3,"Puls.":1,"Sep.":2,"Spira.":1,"Salx-f.":1},"chapter_id":"14"},"Genitalia female, dryness, vagina, menses, after":{"remedies":{"Berb.":1,"Lyc.":2,"Nat-m.":1,"Sep.":2},"chapter_id":"14"},"Genitalia female, dryness, vagina, menses":{"remedies":{"Berb.":1,"Graph.":2,"Lyc.":2,"Nat-m.":1,"Sep.":2},"chapter_id":"14"},"Genitalia female, dryness, vagina, menses, during":{"remedies":{"Graph.":2},"chapter_id":"14"}}