{"Face, clenched jaw":{"remedies":{"Acet-ac.":1,"Acon.":1,"Agar.":1,"Ars.":1,"Bell.":3,"Camph.":1,"Cic.":1,"Colch.":1,"Crot-h.":1,"Cupr.":1,"Dig.":1,"Dios.":1,"Glon.":2,"Hydr-ac.":1,"Hyos.":2,"Ign.":1,"Laur.":1,"Merc.":2,"Nux-v.":1,"Oena.":2,"Op.":2,"Ox-ac.":1,"Phos.":1,"Sil.":2,"Staph.":1,"Stram.":2,"Sulph.":1,"Tarent.":1,"Verat.":2,"Vip.":1,"Posit.":1},"chapter_id":"11"},"Face, clenched jaw, left side":{"remedies":{"Posit.":1},"chapter_id":"11"},"Face, clenched jaw, night":{"remedies":{"Posit.":1},"chapter_id":"11"},"Face, clenched jaw, sleepiness, with":{"remedies":{"Posit.":1},"chapter_id":"11"}}